BuildingWebAppsWithGo/README.md
BuildingWebAppsWithGo/__init__.py
BuildingWebAppsWithGo/__main__.py
BuildingWebAppsWithGo/file.epub
BuildingWebAppsWithGo/index.html
BuildingWebAppsWithGo/css/__init__.py
BuildingWebAppsWithGo/css/annotations.css
BuildingWebAppsWithGo/css/main.css
BuildingWebAppsWithGo/css/normalize.css
BuildingWebAppsWithGo/css/popup.css
BuildingWebAppsWithGo/font/__init__.py
BuildingWebAppsWithGo/font/fontello.eot
BuildingWebAppsWithGo/font/fontello.svg
BuildingWebAppsWithGo/font/fontello.ttf
BuildingWebAppsWithGo/font/fontello.woff
BuildingWebAppsWithGo/img/__init__.py
BuildingWebAppsWithGo/img/annotator-glyph-sprite.png
BuildingWebAppsWithGo/img/annotator-icon-sprite.png
BuildingWebAppsWithGo/img/apple-touch-icon.png
BuildingWebAppsWithGo/img/cancelfullscreen.png
BuildingWebAppsWithGo/img/close.png
BuildingWebAppsWithGo/img/fullscreen.png
BuildingWebAppsWithGo/img/loader.gif
BuildingWebAppsWithGo/img/menu-icon.png
BuildingWebAppsWithGo/img/save.png
BuildingWebAppsWithGo/img/saved.png
BuildingWebAppsWithGo/img/settings-s.png
BuildingWebAppsWithGo/img/settings.png
BuildingWebAppsWithGo/img/star.png
BuildingWebAppsWithGo/js/__init__.py
BuildingWebAppsWithGo/js/epub.js
BuildingWebAppsWithGo/js/epub.min.js
BuildingWebAppsWithGo/js/epub.min.map
BuildingWebAppsWithGo/js/hooks.min.js
BuildingWebAppsWithGo/js/hooks.min.map
BuildingWebAppsWithGo/js/reader.js
BuildingWebAppsWithGo/js/reader.js.map
BuildingWebAppsWithGo/js/reader.min.js
BuildingWebAppsWithGo/js/reader.min.map
BuildingWebAppsWithGo/js/hooks/__init__.py
BuildingWebAppsWithGo/js/hooks/extensions/__init__.py
BuildingWebAppsWithGo/js/hooks/extensions/highlight.js
BuildingWebAppsWithGo/js/libs/__init__.py
BuildingWebAppsWithGo/js/libs/jquery.min.js
BuildingWebAppsWithGo/js/libs/localforage.min.js
BuildingWebAppsWithGo/js/libs/screenfull.js
BuildingWebAppsWithGo/js/libs/screenfull.min.js
BuildingWebAppsWithGo/js/libs/zip.min.js
BuildingWebAppsWithGo/js/plugins/__init__.py
building_web_apps_with_go-2024.3.1.0.dist-info/METADATA
building_web_apps_with_go-2024.3.1.0.dist-info/WHEEL
building_web_apps_with_go-2024.3.1.0.dist-info/entry_points.txt
building_web_apps_with_go-2024.3.1.0.dist-info/top_level.txt
building_web_apps_with_go-2024.3.1.0.dist-info/RECORD
